{"description":"Checkout Flow|Order Placement ","passed":true,"pending":false,"os":"windows","sessionId":"37c235e95051975238a4b1b6f03063e2","instanceId":7460,"browser":{"name":"chrome","version":"83.0.4103.97"},"message":"Passed","browserLogs":[{"level":"SEVERE","message":"https://www.facebook.com/tr/?id=379244549342554&ev=InitiateCheckout&dl=https%3A%2F%2Fcheckout.getaclearrear.com%2Frear214uptest%2Fklav%2Fcheckout%3Fcomments%3Dtrue%26faq%3Dtrue%26proof%3Dtop%26sticky%3Dtrue%26language%3Dus&rl=&if=false&ts=1591436079720&cd[content_type]=product_group&cd[content_ids]=%5B379244549342554%5D&sw=1366&sh=768&v=2.9.18&r=stable&ec=0&o=30&fbp=fb.1.1591436079719.2144251178&it=1591436079431&coo=false&rqm=GET - Failed to load resource: net::ERR_NAME_NOT_RESOLVED","timestamp":1591436083873,"type":""},{"level":"SEVERE","message":"https://www.facebook.com/tr/?id=379244549342554&ev=Microdata&dl=https%3A%2F%2Fcheckout.getaclearrear.com%2Frear214uptest%2Fklav%2Fcheckout%3Fcomments%3Dtrue%26faq%3Dtrue%26proof%3Dtop%26sticky%3Dtrue%26language%3Dus&rl=&if=false&ts=1591436080230&cd[DataLayer]=%5B%5D&cd[Meta]=%7B%22title%22%3A%22Clear%20Rear%E2%84%A2%22%2C%22meta%3Adescription%22%3A%22ClearRear%20description%22%7D&cd[OpenGraph]=%7B%22og%3Asite_name%22%3A%22Clear%20Rear%E2%84%A2%22%2C%22og%3Atitle%22%3A%22Best%20Choice%20for%20Your%20Tush%22%2C%22og%3Adescription%22%3A%22Best%20Choice%20for%20my%20Tush%22%2C%22og%3Aurl%22%3A%22https%3A%2F%2Fgetaclearrear.com%22%2C%22og%3Aimage%22%3A%22https%3A%2F%2Fd3hlrrbqydii6y.cloudfront.net%2Fimg%2F146b699924f4e22565a9e82c1b39cce4.png%22%2C%22og%3Aimage%3Atype%22%3A%22image%2Fpng%22%7D&cd[Schema.org]=%5B%5D&cd[JSON-LD]=%5B%5D&sw=1366&sh=768&v=2.9.18&r=stable&ec=1&o=30&fbp=fb.1.1591436079719.2144251178&it=1591436079431&coo=false&es=automatic&tm=3&rqm=GET - Failed to load resource: net::ERR_NAME_NOT_RESOLVED","timestamp":1591436083874,"type":""},{"level":"SEVERE","message":"https://servedbyadbutler.com/convtrack.spark?MID=178601&CID=375558 - Failed to load resource: net::ERR_CONNECTION_CLOSED","timestamp":1591436135695,"type":""},{"level":"SEVERE","message":"https://servedbyadbutler.com/convtrack.spark?MID=178601&CID=402225 - Failed to load resource: net::ERR_CONNECTION_CLOSED","timestamp":1591436135695,"type":""},{"level":"SEVERE","message":"https://servedbyadbutler.com/convtrack.spark?MID=178601&CID=402224 - Failed to load resource: net::ERR_CONNECTION_CLOSED","timestamp":1591436135695,"type":""},{"level":"SEVERE","message":"https://servedbyadbutler.com/convtrack.spark?MID=178601&CID=402223 - Failed to load resource: net::ERR_CONNECTION_CLOSED","timestamp":1591436135695,"type":""}],"screenShotFile":"00740007-00f5-009d-00d6-00e5008a0067.png","timestamp":1591436073031,"duration":62807}
